{
    "idSave": 1408,
    "isFirstSession": false,
    "language": "en",
    "promptDone": false,
    "money": 40750,
    "power": 3000,
    "bagUpgradesBought": 0,
    "petDropOrderCurrentId": 5,
    "openedSkins": [
        true,
        false,
        false,
        false,
        false,
        false,
        false,
        false,
        false,
        false,
        false,
        false,
        false,
        false,
        false
    ],
    "openedTrails": [
        true,
        false,
        false,
        false,
        false,
        false,
        false
    ],
    "petInventoryItems": [
        0,
        0,
        1,
        0,
        0,
        0
    ],
    "petEggsInventoryItems": [
        0,
        0,
        0,
        0
    ],
    "shopPrices": [
        0
    ],
    "educationPassedCount": 0,
    "skinStoreToastEducationShowed": true,
    "storeToastEducationShowed": false,
    "lastSkinId": 0,
    "lastTrailId": 0,
    "progressBarAmount": 0.08163265138864517,
    "playerRecord": 500,
    "level": 1
}